setup.py
django_jwt/__init__.py
django_jwt.egg-info/PKG-INFO
django_jwt.egg-info/SOURCES.txt
django_jwt.egg-info/dependency_links.txt
django_jwt.egg-info/requires.txt
django_jwt.egg-info/top_level.txt
django_jwt.egg-info/zip-safe